django_rest_camel-0.3.4.dist-info/DESCRIPTION.rst
django_rest_camel-0.3.4.dist-info/METADATA
django_rest_camel-0.3.4.dist-info/RECORD
django_rest_camel-0.3.4.dist-info/WHEEL
django_rest_camel-0.3.4.dist-info/metadata.json
django_rest_camel-0.3.4.dist-info/top_level.txt
drf_camel/__init__.py
drf_camel/parser.py
drf_camel/render.py
drf_camel/settings.py
drf_camel/util.py
rest_camel/__init__.py
rest_camel/parser.py
rest_camel/render.py
rest_camel/settings.py
rest_camel/util.py
