Metadata-Version: 2.0
Name: django-rest-camel
Version: 0.3.4
Summary: Camel case support for Django REST Framework.
Home-page: https://github.com/dekoza/django-rest-camel
Author: Dominik Kozaczko
Author-email: dominik@kozaczko.info
License: BSD
Keywords: djangorestframework_camel django rest camelcase camel
Platform: UNKNOWN
Classifier: Development Status :: 3 - Alpha
Classifier: Intended Audience :: Developers
Classifier: License :: OSI Approved :: BSD License
Classifier: Natural Language :: English
Classifier: Programming Language :: Python :: 2
Classifier: Programming Language :: Python :: 2.7
Classifier: Programming Language :: Python :: 3
Classifier: Programming Language :: Python :: 3.5
Classifier: Programming Language :: Python :: 3.6
